pyakri_de_filters/__init__.py
pyakri_de_filters/data/models/convnext_base_fb_in22k_ft_in1k.onnx
pyakri_de_filters/data/models/convnext_base_fb_in22k_ft_in1k_patch.onnx
pyakri_de_filters/data/models/dinov2_vits14.onnx
pyakri_de_filters/data/models/dinov2_vits14_patch_8x8.onnx
pyakri_de_filters/data/models/mobilenet_v2_035_224.onnx
pyakri_de_filters/data/models/mobilenet_v2_035_224_patch.onnx
pyakri_de_filters/data/models/openai_clip_vit_b32.onnx
pyakri_de_filters/data/models/openclip_clip_vit_b32.onnx
pyakri_de_filters/data/models/tiny_vit_5m_224_in22k.onnx
pyakri_de_filters/data/models/tiny_vit_5m_224_in22k_patch.onnx
pyakri_de_filters/data/preprocessors/convnext_base_fb_in22k_ft_in1k.preprocessor
pyakri_de_filters/data/preprocessors/convnext_base_fb_in22k_ft_in1k_patch.preprocessor
pyakri_de_filters/data/preprocessors/dinov2_vits14.preprocessor
pyakri_de_filters/data/preprocessors/dinov2_vits14_patch_8x8.preprocessor
pyakri_de_filters/data/preprocessors/mobilenet_v2_035_224.preprocessor
pyakri_de_filters/data/preprocessors/mobilenet_v2_035_224_patch.preprocessor
pyakri_de_filters/data/preprocessors/openai_clip_vit_b32.preprocessor
pyakri_de_filters/data/preprocessors/openclip_clip_vit_b32.preprocessor
pyakri_de_filters/data/preprocessors/tiny_vit_5m_224_in22k.preprocessor
pyakri_de_filters/data/preprocessors/tiny_vit_5m_224_in22k_patch.preprocessor
pyakri_de_filters/data_ingest_filter/__init__.py
pyakri_de_filters/data_ingest_filter/data_ingest_raw_data_helper.py
pyakri_de_filters/featurizers/__init__.py
pyakri_de_filters/featurizers/featurizer.py
pyakri_de_filters/featurizers/featurizer_aggregator.py
pyakri_de_filters/featurizers/image_featurizer.py
pyakri_de_filters/featurizers/split_featurizer.py
pyakri_de_filters/preprocessors/__init__.py
pyakri_de_filters/preprocessors/default_preprocessor_wrapper.py
pyakri_de_filters/preprocessors/enums.py
pyakri_de_filters/preprocessors/grayscale_preprocessor.py
pyakri_de_filters/preprocessors/main.py
pyakri_de_filters-1.25.0.dev0.dist-info/METADATA
pyakri_de_filters-1.25.0.dev0.dist-info/WHEEL
pyakri_de_filters-1.25.0.dev0.dist-info/top_level.txt
pyakri_de_filters-1.25.0.dev0.dist-info/RECORD
