Metadata-Version: 2.4
Name: pyakri_de_filters
Version: 1.25.0.dev0
Summary: Python based filters using CPU resource
Author: Akridata Inc
Author-email: support@akridata.com
Classifier: Programming Language :: Python :: 3
Classifier: Operating System :: OS Independent
Requires-Dist: data_ingest_filters==1.25.0.dev0
Requires-Dist: matplotlib>=3.7.2
Requires-Dist: numba>=0.57.1
Requires-Dist: numpy>=1.19.2
Requires-Dist: pandas>=1.5.1
Requires-Dist: pyakri_de_utils==1.25.0.dev0
Requires-Dist: pyarrow==14.0.1
Requires-Dist: scikit-image>=0.21.0
Requires-Dist: scipy>=1.9.3
Requires-Dist: tqdm>=4.64.0
Requires-Dist: urllib3==1.26.19
Provides-Extra: cpu
Requires-Dist: pyakri_de_utils[cpu]==1.25.0.dev0; extra == "cpu"
Provides-Extra: gpu
Requires-Dist: pyakri_de_utils[gpu]==1.25.0.dev0; extra == "gpu"
Provides-Extra: test
Requires-Dist: pyakri_de_utils[gpu]==1.25.0.dev0; extra == "test"
Requires-Dist: pytest; extra == "test"
Dynamic: author
Dynamic: author-email
Dynamic: classifier
Dynamic: provides-extra
Dynamic: requires-dist
Dynamic: summary
